llm_tool_harness/__init__.py
llm_tool_harness/agent.py
llm_tool_harness/exceptions.py
llm_tool_harness/tool.py
llm_tool_harness/utils.py
llm_tool_harness/providers/__init__.py
llm_tool_harness/providers/anthropic.py
llm_tool_harness/providers/base.py
llm_tool_harness-0.1.1.dist-info/licenses/LICENSE
llm_tool_harness-0.1.1.dist-info/METADATA
llm_tool_harness-0.1.1.dist-info/WHEEL
llm_tool_harness-0.1.1.dist-info/top_level.txt
llm_tool_harness-0.1.1.dist-info/RECORD
