Metadata-Version: 2.4
Name: llm_tool_harness
Version: 0.1.1
Summary: A library to easily build LLM agents with tool-using capabilities.
Author-email: zhu-weijie <byzhubaiyuan@gmail.com>
License: MIT License
Project-URL: Homepage, https://github.com/zhu-weijie/llm-tool-harness
Project-URL: Bug Tracker, https://github.com/zhu-weijie/llm-tool-harness/issues
Classifier: Programming Language :: Python :: 3
Classifier: Operating System :: OS Independent
Classifier: Intended Audience :: Developers
Classifier: Topic :: Scientific/Engineering :: Artificial Intelligence
Classifier: Topic :: Software Development :: Libraries :: Python Modules
Requires-Python: >=3.8
License-File: LICENSE
Requires-Dist: anthropic~=0.52.0
Provides-Extra: dev
Requires-Dist: build; extra == "dev"
Requires-Dist: twine; extra == "dev"
Requires-Dist: ruff; extra == "dev"
Requires-Dist: pytest; extra == "dev"
Requires-Dist: pytest-cov; extra == "dev"
Requires-Dist: python-dotenv; extra == "dev"
Provides-Extra: test
Requires-Dist: pytest; extra == "test"
Requires-Dist: pytest-cov; extra == "test"
Dynamic: license-file
